setup.py
snailwebs/__init__.py
snailwebs/seeyon/__init__.py
snailwebs/seeyon/ops/__init__.py
snailwebs_seeyon_ops.egg-info/PKG-INFO
snailwebs_seeyon_ops.egg-info/SOURCES.txt
snailwebs_seeyon_ops.egg-info/dependency_links.txt
snailwebs_seeyon_ops.egg-info/top_level.txt