Metadata-Version: 1.0
Name: snailwebs-seeyon-ops
Version: 0.0.2
Summary: 致远协同办公系统运维工具
Home-page: UNKNOWN
Author: snail
Author-email: snail_email@163.com
License: UNKNOWN
Platform: UNKNOWN
